{
    "biome": "digital",
    "grid": [
        20,
        20
    ],
    "monkeyStart": [
        0,
        0
    ],
    "bananas": [
        {
            "x": 19,
            "y": 19
        },
        {
            "x": 19,
            "y": 0
        },
        {
            "x": 0,
            "y": 19
        }
    ],
    "switches": [
        {
            "x": 10,
            "y": 10,
            "gateId": 1
        }
    ],
    "gates": [
        {
            "x": 11,
            "y": 11,
            "gateId": 1
        }
    ],
    "teleporters": [
        {
            "x": 1,
            "y": 1,
            "pairId": 1
        },
        {
            "x": 18,
            "y": 18,
            "pairId": 1
        }
    ],
    "stars": {
        "3": 60,
        "2": 100
    }
}